[
  {
    "id": 180,
    "title": "Germany’s policy on China: From win-win to strategic competition",
    "url": "https://www.atlanticcouncil.org/in-depth-research-reports/report/germanys-policy-on-china-from-win-win-to-strategic-competition/",
    "source": "www.atlanticcouncil.org",
    "description": "This is the fifth chapter of the report “Is Europe waking up to the China challenge? How geopolitics are reshaping EU and transatlantic strategy.” Read the full report here.\n\n\n\n\n\nGermany’s relationship with China has evolved significantly over the past decades, with economic cooperation forming the ...",
    "category": "Trade Policy",
    "country": "China",
    "published_date": "2025-11-10"
  }
]