[
  {
    "id": 3983,
    "title": "Sao Tome and Principe",
    "url": "https://www.jagranjosh.com/general-knowledge/sao-tome-and-principe-1292321490-1",
    "source": "www.jagranjosh.com",
    "description": "National name: Rep\u00fablica Democr\u00e1tica de S\u00e3o Tom\u00e9 e Pr\u00edncipe\n\nGovernment\n\nRepublic.\n\nGeography\n\nThe tiny volcanic islands of S\u00e3o Tom\u00e9 and Pr\u00edncipe lie in the Gulf of Guinea about 150 mi (240 km) off West Africa. S\u00e3o Tom\u00e9 (about 330 sq mi; 859 sq km) is covered by a dense mountainous jungle, out of wh...",
    "category": "Economy",
    "country": "Sao Tome and Principe",
    "published_date": "2010-12-01"
  }
]