[
  {
    "id": 762,
    "title": "Stock market today: Wall Street dips as hopes dim for an imminent cut to interest rates",
    "url": "https://www.hindustantimes.com/world-news/stock-market-today-wall-street-slips-as-hopes-dim-for-an-imminent-cut-to-interest-rates-101705525528025.html",
    "source": "www.hindustantimes.com",
    "description": "NEW YORK (AP) \u2014 Wall Street slipped Wednesday following another signal that it may have gotten too optimistic about when the Federal Reserve will deliver the cuts to interest rates that traders crave so much. HT Image\n\nThe S&P 500 fell 26.77 points, or 0.6%, to 4,739.21. It\u2019s the second straight stu...",
    "category": "Interest Rates",
    "country": "Albania",
    "published_date": "2024-01-01"
  }
]