[
  {
    "id": 3556,
    "title": "North Korea and Russia agree to expand their economic cooperation",
    "url": "https://www.thehindu.com/news/international/north-korea-and-russia-agree-to-expand-their-economic-cooperation/article68892865.ece",
    "source": "www.thehindu.com",
    "description": "North Korea and Russia reached a new agreement for expanding economic cooperation following high-level talks in Pyongyang this week, the North\u2019s state media said Thursday (November 21, 2024), as they continue to align in the face of their confrontations with Washington.\n\nNorth Korea\u2019s official Korea...",
    "category": "Economic Growth",
    "country": "North Korea",
    "published_date": "2024-11-01"
  }
]