[
  {
    "id": 2080,
    "title": "Tax Russia to rebuild Ukraine and increase defence spending, Estonia says",
    "url": "https://www.hindustantimes.com/world-news/tax-russia-to-rebuild-ukraine-and-increase-defence-spending-estonia-says-101734352818039.html",
    "source": "www.hindustantimes.com",
    "description": "By Andrius Sytas Tax Russia to rebuild Ukraine and increase defence spending, Estonia says\n\nTALLINN, - Estonia will propose that the leaders of the United Kingdom-led alliance of northern European NATO countries spend no less than 2.5% of GDP on defence in response to the threat from Russia.\n\nOnly 2...",
    "category": "GDP",
    "country": "Estonia",
    "published_date": "2024-12-01"
  }
]