[
  {
    "id": 4749,
    "title": "How to exchange torn currency notes: Bank branches, procedure, limit and details",
    "url": "https://www.hindustantimes.com/business/how-to-exchange-torn-currency-notes-bank-branches-procedure-limit-and-details-101715675131579.html",
    "source": "www.hindustantimes.com",
    "description": "You can exchange soiled or defective notes in any banks all over the country although the rules are different when it comes to exchanging notes in small amounts and in bulk. As per the Reserve Bank of India (RBI) website, \u201cA \u2018soiled note\u2019 means a note which has become dirty due to normal wear and te...",
    "category": "Currency Exchange Rates",
    "country": "Tuvalu",
    "published_date": "2024-05-01"
  }
]