[
  {
    "id": 1752,
    "title": "RBI retains India's GDP growth forecast for current fiscal at 6.5% amid geopolitical tensions",
    "url": "https://www.hindustantimes.com/india-news/rbi-retains-indias-gdp-growth-forecast-for-current-fiscal-at-6-5-amid-geopolitical-tensions-101749185964465.html",
    "source": "www.hindustantimes.com",
    "description": "RBI Governor Sanjay Malhotra on Friday estimated the country's real GDP growth at 6.5 per cent for the fiscal year 2025-26. Reserve Bank of India (RBI) Governor Sanjay Malhotra makes a statement on RBI Monetary Policy.(ANI )\n\nMalhotra made the prediction while announcing the RBI's bimonthly monetary...",
    "category": "Fiscal Policy",
    "country": "Cuba",
    "published_date": "2025-06-01"
  }
]