[
  {
    "id": 2729,
    "title": "Japan PM shuts down resignation rumours, says will focus on trade deal with US",
    "url": "https://www.hindustantimes.com/world-news/japan-pm-shigeru-ishiba-shuts-down-resignation-rumours-says-will-focus-on-trade-deal-with-us-101753257625642.html",
    "source": "www.hindustantimes.com",
    "description": "Japanese Prime Minister Shigeru Ishiba denied reports he plans to announce his resignation over a historic defeat of his ruling party in a weekend election, saying instead he wanted to make sure a new tariff agreement with the United States is appropriately implemented. Japan's Prime Minister and Pr...",
    "category": "Trade Policy",
    "country": "Japan",
    "published_date": "2025-07-01"
  }
]