[
  {
    "id": 3628,
    "title": "India, Oman to sign CEPA trade pact very soon: Oman's Ambassador to India",
    "url": "https://www.thehindu.com/news/national/india-oman-to-sign-cepa-trade-pact-very-soon-omans-ambassador-to-india/article70076426.ece",
    "source": "www.thehindu.com",
    "description": "India and Oman are set to sign the Comprehensive Economic Partnership Agreement (CEPA) \"very soon\" with both nations eyeing diversification of their trade basket to include more commodities and exchange of services, the country's Ambassador to India Issa Saleh Abdullah Saleh Alshibani said.\n\nIn an i...",
    "category": "Trade Policy",
    "country": "Oman",
    "published_date": "2025-09-01"
  }
]