[
  {
    "id": 4368,
    "title": "U.S., Chinese officials to launch talks in Spain on trade irritants, TikTok deadline",
    "url": "https://www.thehindu.com/news/international/us-chinese-officials-talks-in-spain-on-trade-irritants-tiktok-deadline/article70048265.ece",
    "source": "www.thehindu.com",
    "description": "U.S. and Chinese officials meet in Madrid on Sunday (September 14, 2025) to hash over longstanding trade irritants, a looming divestiture deadline for Chinese short video app TikTok and demands by Washington that G7 and European allies impose tariffs on China to halt its purchases of Russian oil.\n\nT...",
    "category": "Trade Policy",
    "country": "Spain",
    "published_date": "2025-09-01"
  }
]