[
  {
    "id": 1836,
    "title": "Vance Boelter seen speaking at Democratic Republic of the Congo's seminar, videos surface | Watch",
    "url": "https://www.hindustantimes.com/world-news/us-news/vance-boelter-seen-speaking-at-democratic-republic-of-the-congos-seminar-videos-surface-watch-101749961619170.html",
    "source": "www.hindustantimes.com",
    "description": "As police seek to arrest Minnesota assassin Vance Luther Boelter, videos that have surfaced on social media show him speaking at a seminar held jointly by the Democratic Republic of the Congo and the Minnesota Africans United and Global Minnesota. Boelter is being sought in connection to several sho...",
    "category": "Inflation",
    "country": "Democratic Republic of the Congo",
    "published_date": "2025-06-01"
  }
]