[
  {
    "id": 2853,
    "title": "Kuwait Cabinet Approves Debt Law, Paving Way for Bond Sales",
    "url": "https://www.livemint.com/economy/kuwait-cabinet-approves-debt-law-paving-way-for-bond-sales-11741912270517.html",
    "source": "www.livemint.com",
    "description": "(Bloomberg) -- Kuwait\u2019s Council of Ministers approved a draft decree that paves the way for the OPEC-member Gulf state to sell debt for the first time in eight years.\n\nThe cabinet approved a draft law on \u201cfinancing and liquidity,\u201d according to a statement released after Thursday\u2019s meeting, in refere...",
    "category": "Economy",
    "country": "Kuwait",
    "published_date": "2025-03-01"
  }
]