[
  {
    "id": 1879,
    "title": "India needs a new fiscal policy framework: Here\u2019s why",
    "url": "https://www.livemint.com/opinion/online-views/india-fiscal-policy-framework-budget-2025-public-debt-nirmala-sitharaman-budget-speech-monetary-policy-gdp-incentive-11737357189511.html",
    "source": "www.livemint.com",
    "description": "The logic of making public debt the nominal anchor of Indian fiscal policy is not without merit, since what really matters in terms of public finance is the eventual stock of debt that a government will accumulate over the medium term rather than the annual additions to it, aka the fiscal deficit. T...",
    "category": "Fiscal Policy",
    "country": "Djibouti",
    "published_date": "2025-01-01"
  }
]