[
  {
    "id": 4965,
    "title": "Where Trump's Tariffs Stand Going Into 2026",
    "url": "https://finance.yahoo.com/news/where-trumps-tariffs-stand-going-220523161.html",
    "source": "finance.yahoo.com",
    "description": "Spencer Platt / Getty Images There has been a deluge of tariff announcements out of the Trump administration in 2025. Here's where they stand as the year winds down.\n\nKey Takeaways\n\nPresident Trump has imposed a wide range of tariffs throughout 2025, frequently changing or adding new trade measures ...",
    "category": "Trade Policy",
    "country": "Vanuatu",
    "published_date": "2025-12-01"
  }
]