[
  {
    "id": 5026,
    "title": "Vietnam\u2019s raw trade deal with the US isn\u2019t good news",
    "url": "https://www.livemint.com/opinion/online-views/vietnam-us-trade-deal-donald-trump-tariffs-export-duty-transshipment-tariff-barrier-asymmetry-protectionism-hanoi-wto-11751555519851.html",
    "source": "www.livemint.com",
    "description": "If cargo sent from Vietnam happens to be a trans-shipment of merchandise made elsewhere, then that tariff barrier would rise to 40%. This is a device to stop exporters from using its ports to game the US-set matrix of tariffs that vary from one country to another based on a puzzling formula.",
    "category": "Trade Policy",
    "country": "Vietnam",
    "published_date": "2025-07-01"
  }
]