{
  "id": 198,
  "date": "2025-12-01",
  "country": "Vanuatu",
  "summary_text": "## Vanuatu Economic Summary - December 1, 2025\n\n**Date:** December 1, 2025\n\n**Prepared by:** Expert Economic Analyst\n\n### Overview\n\nToday's economic landscape for Vanuatu is primarily shaped by external factors, specifically the evolving global trade policies, particularly those emanating from the United States. While no direct domestic news items regarding Vanuatu's core economic indicators were released today, the potential implications of international trade developments warrant close attention. The continued imposition and potential adjustments of tariffs by major economic blocs, including the United States, could have downstream effects on Vanuatu's trade flows, import costs, and competitiveness.\n\n---\n\n### Trade & International Relations\n\n*   **US Tariff Landscape and Potential Implications for Vanuatu:** A significant development reported today, \"Where Trump's Tariffs Stand Going Into 2026\" (finance.yahoo.com), details the wide range of tariff announcements and changes made by the Trump administration throughout 2025.\n    *   **Implication for Vanuatu:** While the article focuses on US domestic and broader international trade impacts, Vanuatu, as a small island developing state reliant on international trade, could be indirectly affected. Any shifts in global supply chains or increased costs for imported goods (from countries targeted by US tariffs) could impact Vanuatu's import bill and the prices of essential commodities for its citizens and businesses. Furthermore, if Vanuatu exports goods that are subject to US tariffs, or if its trading partners face retaliatory measures that disrupt their economies, Vanuatu's export markets could be indirectly constrained.\n    *   **Key Consideration:** It is crucial for Vanuatu's economic policymakers to monitor how these US tariffs evolve and to assess their specific impact on Vanuatu's key trading partners and the cost of imported goods. Diversification of trade partners and a proactive approach to trade agreements will be vital in mitigating potential negative consequences.\n\n---\n\n### Other Economic Areas (No Specific News Today)\n\n**GDP & Economic Growth:** No specific data or analysis regarding Vanuatu's GDP or economic growth prospects was released today. However, global trade uncertainties, as highlighted by the US tariff news, can cast a shadow over the economic outlook for many nations, including those reliant on international trade like Vanuatu.\n\n**Inflation & Monetary Policy:** No specific inflation data or monetary policy announcements were made for Vanuatu today. Global commodity price fluctuations, which can be influenced by trade policies, remain a potential driver of inflation.\n\n**Fiscal Policy & Government Actions:** No new fiscal policy announcements or government actions impacting the economy were reported for Vanuatu today.\n\n**Labor Market & Unemployment:** No updates on Vanuatu's labor market or unemployment figures were available today. Broader economic trends, including those influenced by trade, can ultimately affect employment levels.\n\n**Currency & Exchange Rates:** No specific news or fluctuations regarding Vanuatu's currency (Vatu) against major international currencies were reported today. However, significant shifts in global trade dynamics can sometimes lead to indirect currency pressures.\n\n---\n\n### Emerging Themes and Outlook\n\nThe primary emerging theme from today's limited economic news is the **significant influence of external trade policy decisions on Vanuatu's economy.** The continuous adjustments and impositions of tariffs by major economic powers like the United States underscore the interconnectedness of the global economy and the vulnerability of smaller nations to such shifts.\n\n**Outlook:** As 2025 concludes, Vanuatu's economic trajectory will likely continue to be influenced by the unfolding global trade landscape. Policymakers should prioritize analyzing the specific impacts of international trade measures on import costs, export competitiveness, and the overall business environment. Proactive strategies in trade diversification, fostering domestic resilience, and leveraging regional economic cooperation will be paramount in navigating potential headwinds and ensuring sustained economic stability.",
  "article_count": 1,
  "generated_at": "2025-12-06T06:15:02.238477",
  "sentiment_score": -0.115
}